simba_ml/__init__.py
simba_ml/_version.py
simba_ml/error_handler.py
simba_ml/cli/__init__.py
simba_ml/cli/__main__.py
simba_ml/cli/generate_data.py
simba_ml/cli/start_prediction.py
simba_ml/cli/problem_viewer/__init__.py
simba_ml/cli/problem_viewer/problem_viewer.py
simba_ml/cli/problem_viewer/run_problem_viewer.py
simba_ml/example_problems/__init__.py
simba_ml/example_problems/constant_function.py
simba_ml/example_problems/salt_and_brine_tanks.py
simba_ml/example_problems/sir.py
simba_ml/example_problems/sird.py
simba_ml/example_problems/trigonometry.py
simba_ml/prediction/__init__.py
simba_ml/prediction/export.py
simba_ml/prediction/normalizer.py
simba_ml/prediction/plugin_loader.py
simba_ml/prediction/preprocessing.py
simba_ml/prediction/logging/__init__.py
simba_ml/prediction/logging/logging_config.py
simba_ml/prediction/logging/wandb_logger.py
simba_ml/prediction/steady_state/__init__.py
simba_ml/prediction/steady_state/config/__init__.py
simba_ml/prediction/steady_state/config/steady_state_data_config.py
simba_ml/prediction/steady_state/data_loader/__init__.py
simba_ml/prediction/steady_state/data_loader/dataset_generator.py
simba_ml/prediction/steady_state/data_loader/mixed_data_loader.py
simba_ml/prediction/steady_state/data_loader/splits.py
simba_ml/prediction/time_series/__init__.py
simba_ml/prediction/time_series/config/__init__.py
simba_ml/prediction/time_series/config/time_series_config.py
simba_ml/prediction/time_series/config/mixed_data_pipeline/__init__.py
simba_ml/prediction/time_series/config/mixed_data_pipeline/data_config.py
simba_ml/prediction/time_series/config/mixed_data_pipeline/pipeline_config.py
simba_ml/prediction/time_series/config/synthetic_data_pipeline/__init__.py
simba_ml/prediction/time_series/config/synthetic_data_pipeline/data_config.py
simba_ml/prediction/time_series/config/synthetic_data_pipeline/pipeline_config.py
simba_ml/prediction/time_series/config/transfer_learning_pipeline/__init__.py
simba_ml-1.0.0rc15.dist-info/METADATA
simba_ml-1.0.0rc15.dist-info/WHEEL
simba_ml-1.0.0rc15.dist-info/entry_points.txt
simba_ml-1.0.0rc15.dist-info/top_level.txt
simba_ml-1.0.0rc15.dist-info/RECORD
