Metadata-Version: 2.1
Name: simba-ml
Version: 1.0.0rc15
Summary: Simulation-Based Machine Learning
Home-page: UNKNOWN
Author: Maximilian Kleissl, Björn Heyder, Julian Zabbarov, Lukas Drews
Author-email: maximilian.kleissl@student.hpi.de,bjoern.heyder@student.hpi.de,julian.zabbarov@student.hpi.de,lukas.drews@student.hpi.de
License: UNKNOWN
Project-URL: Bug Tracker, https://github.com/DILiS-lab/SimbaML/issues
Project-URL: Source Code, https://github.com/DILiS-lab/SimbaML
Project-URL: Documentation, https://simbaml.readthedocs.io
Keywords: python,machine learning,simulation,ordinary differential equations,ode,simba,simba-ml
Platform: UNKNOWN
Requires-Dist: streamlit
Requires-Dist: pandas
Requires-Dist: numpy
Requires-Dist: scipy
Requires-Dist: matplotlib
Requires-Dist: scikit-learn
Requires-Dist: dacite
Requires-Dist: tomli
Requires-Dist: wandb
